{
	"response": [
		{
			"maintainer": "KamiKaonashi",
			"oem": "Xiaomi",
			"device": "Xiaomi Mi 11",
			"filename": "AlphaDroid-13.0-20230720-venus-full_gapps-v1.7.zip",
			"download": "https://sourceforge.net/projects/alphadroid-project/files/venus/AlphaDroid-13.0-20230720-venus-full_gapps-v1.7.zip/download",
			"timestamp": 1689867936,
			"md5": "59f3c6dcaadfc00dfcd1bc7734b5e2ca",
			"sha256": "7dce3937aaf17feb308d95b0a2e3f6caeeee902f5d94c8963ccd101edf6559fc",
			"size": 2213221017,
			"version": "1.7",
			"buildtype": "full_gapps",
			"forum": "https://forum.xda-developers.com/m/kamikaonashi.4696609/",
			"gapps": "",
			"firmware": "",
			"modem": "",
			"bootloader": "",
			"recovery": "",
			"paypal": "",
			"telegram": "https://t.me/kamikaonashi",
			"dt": "https://github.com/AlphaDroid-devices/device_xiaomi_venus",
			"common-dt": "https://github.com/AlphaDroid-devices/device_xiaomi_sm8350-common",
			"kernel": "https://github.com/AlphaDroid-devices/kernel_xiaomi_venus"
		}
	]
}
